app/__init__.py
app/config.py
app/main.py
app/test.py
app/test_csv.py
app/test_methods.py
versdatetool-1.0.4.dist-info/LICENSE.txt
versdatetool-1.0.4.dist-info/METADATA
versdatetool-1.0.4.dist-info/WHEEL
versdatetool-1.0.4.dist-info/entry_points.txt
versdatetool-1.0.4.dist-info/top_level.txt
versdatetool-1.0.4.dist-info/RECORD
