Metadata-Version: 2.1
Name: versdatetool
Version: 1.0.4
Summary: Package making for simple CLI AUTOMATION TOOL FOR QUICK pr GENERATION.
Home-page: https://github.com/dyte-submissions/dyte-vit-2022-surya-x
Author: V Surya kumar
Author-email: kumarsurya.2001@gmail.com
License: MIT
Keywords: Dyte SDK Tooling CLI Tool
Platform: UNKNOWN
Classifier: Programming Language :: Python :: 3
Classifier: License :: OSI Approved :: MIT License
Classifier: Operating System :: OS Independent
Requires-Dist: requests
Requires-Dist: pytest
Requires-Dist: pytest-shutil
Requires-Dist: pybase64
Requires-Dist: GitPython
Requires-Dist: argparse
Requires-Dist: packaging
